{"_id":"5bacd58851aef21b38c72c76","success":true,"returnCode":"1001","returnMessage":null,"data":{"filter":{"title":"美丽说wap首页","list":[{"fcid":"10057922","style":null,"sort":"pop","title":"流行","type":"sort"},{"fcid":"10057922","style":null,"sort":"sell","title":"热销","type":"sort"},{"fcid":"10057922","style":null,"sort":"new","title":"上新","type":"sort"}]},"total":41680,"param":{"eventId":70003,"cKey":"wap-index","fcid":"10057922","cpcEventId":70005,"section":"0","_mgjuuid":"c7b89d60-18aa-4a7b-8842-c80c0784c0cb","sort":"sell","page":"17","ptpWallDoc":"_wall_docs","ptpPartC":"_mb_mls_10057922_wap-index_noab-noab","cpc_offset":0,"ptpWallCpc":"_wall_cpc"},"page":17,"sort":"sell","list":[{"itemType":5,"ptpC":"_mb_mls_10057922_wap-index_noab-noab","titleTags":null,"clientUrl":"http://item.meilishuo.com/h5/detail/1m7iafi?acm=3.ms.0_4_1m7iafi.0.13385-69004.ni0a5r4QXJkto.t_-sd_117-lc_16","iid":"1m7iafi","showLarge":{"img":"http://s11.mogucdn.com/mlcdn/c45406/180821_7d6j48i8bc679kfib7h5b6f73dji4_640x960.jpg_560x999.jpg","w":560,"h":840},"link":"http://item.meilishuo.com/h5/detail/1m7iafi?acm=3.ms.0_4_1m7iafi.0.13385-69004.ni0a5r4QXJkto.t_-sd_117-lc_16","show":{"img":"http://s3.mogucdn.com/mlcdn/c45406/180821_7d6j48i8bc679kfib7h5b6f73dji4_640x960.jpg_320x999.jpg","w":320,"h":416},"itemMarks":"1525","acm":"3.ms.0_4_1m7iafi.0.13385-69004.ni0a5r4QXJkto.t_-sd_117-lc_16","type":2,"title":"2018秋新款露腰韩版修身小心机系带针织连衣裙气质长袖毛衣裙","orgPrice":"￥141.43","cparam":null,"props":["2018秋新款露腰韩版修身小心机系带针织连衣裙气质长袖毛衣裙"],"lefttop_taglist":[],"sale":721,"price":"99.00","cfav":2,"leftbottom_taglist":[],"shopId":21575222,"popularStar":0},{"itemType":5,"ptpC":"_mb_mls_10057922_wap-index_noab-noab","titleTags":null,"clientUrl":"http://item.meilishuo.com/h5/detail/1m72uv6?acm=3.ms.0_4_1m72uv6.0.13385-69004.ni0a5r4QXJkto.t_-sd_117-lc_16","iid":"1m72uv6","showLarge":{"img":"http://s11.mogucdn.com/mlcdn/55cf19/180809_22hla4ec1ff5f2al24l8862i0c0ka_640x960.jpg_560x999.jpg","w":560,"h":840},"link":"http://item.meilishuo.com/h5/detail/1m72uv6?acm=3.ms.0_4_1m72uv6.0.13385-69004.ni0a5r4QXJkto.t_-sd_117-lc_16","show":{"img":"http://s11.mogucdn.com/mlcdn/55cf19/180809_22hla4ec1ff5f2al24l8862i0c0ka_640x960.jpg_320x999.jpg","w":320,"h":416},"itemMarks":"-1","acm":"3.ms.0_4_1m72uv6.0.13385-69004.ni0a5r4QXJkto.t_-sd_117-lc_16","type":2,"title":"2018秋装新款修身长款蕾丝毛衣裙过膝修身打底衫针织连衣裙中长款半高领套头上衣","orgPrice":"￥113.00","cparam":null,"props":["2018秋装新款修身长款蕾丝毛衣裙过膝修身打底衫针织连衣裙中长款半高领套头上衣"],"lefttop_taglist":[],"sale":718,"price":"113.00","cfav":0,"leftbottom_taglist":[],"shopId":1302408860,"popularStar":0},{"itemType":5,"ptpC":"_mb_mls_10057922_wap-index_noab-noab","titleTags":null,"clientUrl":"http://item.meilishuo.com/h5/detail/1m6v3uc?acm=3.ms.0_4_1m6v3uc.0.13385-69004.ni0a5r4QXJkto.t_-sd_117-lc_16","iid":"1m6v3uc","showLarge":{"img":"http://s11.mogucdn.com/mlcdn/55cf19/180804_67c9g3f1el33la34ah1k1f53h64hf_640x960.jpg_560x999.jpg","w":560,"h":840},"link":"http://item.meilishuo.com/h5/detail/1m6v3uc?acm=3.ms.0_4_1m6v3uc.0.13385-69004.ni0a5r4QXJkto.t_-sd_117-lc_16","show":{"img":"http://s11.mogucdn.com/mlcdn/55cf19/180804_67c9g3f1el33la34ah1k1f53h64hf_640x960.jpg_320x999.jpg","w":320,"h":416},"itemMarks":"-1","acm":"3.ms.0_4_1m6v3uc.0.13385-69004.ni0a5r4QXJkto.t_-sd_117-lc_16","type":2,"title":"2018秋装女装韩版新款小清新休闲宽松时尚上衣心机长袖白色简约衬衫+裤子两件套时尚套装女韩","orgPrice":"￥198.00","cparam":null,"props":["2018秋装女装韩版新款小清新休闲宽松时尚上衣心机长袖白色简约衬衫+裤子两件套时尚套装女韩"],"lefttop_taglist":[],"sale":717,"price":"198.00","cfav":17,"leftbottom_taglist":[],"shopId":1302421384,"popularStar":0},{"itemType":5,"ptpC":"_mb_mls_10057922_wap-index_noab-noab","titleTags":null,"clientUrl":"http://item.meilishuo.com/h5/detail/1m6oamq?acm=3.ms.0_4_1m6oamq.0.13385-69004.ni0a5r4QXJkto.t_-sd_117-lc_16","iid":"1m6oamq","showLarge":{"img":"http://s3.mogucdn.com/mlcdn/c45406/180731_89if5de1aj1d20h546acfk75cj13l_640x960.jpg_560x999.jpg","w":560,"h":840},"link":"http://item.meilishuo.com/h5/detail/1m6oamq?acm=3.ms.0_4_1m6oamq.0.13385-69004.ni0a5r4QXJkto.t_-sd_117-lc_16","show":{"img":"http://s11.mogucdn.com/mlcdn/c45406/180731_89if5de1aj1d20h546acfk75cj13l_640x960.jpg_320x999.jpg","w":320,"h":416},"itemMarks":"-1","acm":"3.ms.0_4_1m6oamq.0.13385-69004.ni0a5r4QXJkto.t_-sd_117-lc_16","type":2,"title":"2018秋装新款漏洞红色柔软中袖套头毛衣镂空上衣+黑色背心长裙连衣裙两件套装女","orgPrice":"￥128.00","cparam":null,"props":["2018秋装新款漏洞红色柔软中袖套头毛衣镂空上衣+黑色背心长裙连衣裙两件套装女"],"lefttop_taglist":[],"sale":715,"price":"89.60","cfav":76,"leftbottom_taglist":[],"shopId":107897,"popularStar":0},{"itemType":5,"ptpC":"_mb_mls_10057922_wap-index_noab-noab","titleTags":null,"clientUrl":"http://item.meilishuo.com/h5/detail/1ls3htm?acm=3.ms.0_4_1ls3htm.0.13385-69004.ni0a5r4QXJkto.t_-sd_117-lc_16","iid":"1ls3htm","showLarge":{"img":"http://s3.mogucdn.com/mlcdn/c45406/180302_0a77ibkhigfh6je4fdli41742af52_640x960.jpg_560x999.jpg","w":560,"h":840},"link":"http://item.meilishuo.com/h5/detail/1ls3htm?acm=3.ms.0_4_1ls3htm.0.13385-69004.ni0a5r4QXJkto.t_-sd_117-lc_16","show":{"img":"http://s3.mogucdn.com/mlcdn/c45406/180302_0a77ibkhigfh6je4fdli41742af52_640x960.jpg_320x999.jpg","w":320,"h":416},"itemMarks":"1525 1964 353 181","acm":"3.ms.0_4_1ls3htm.0.13385-69004.ni0a5r4QXJkto.t_-sd_117-lc_16","type":2,"title":"2018秋季新款韩版小清新学院学生蝴蝶结长袖针织毛衣马甲两件套衬衫","orgPrice":"￥127.15","cparam":null,"props":["2018秋季新款韩版小清新学院学生蝴蝶结长袖针织毛衣马甲两件套衬衫"],"lefttop_taglist":[],"sale":712,"price":"89.00","cfav":159,"leftbottom_taglist":[],"shopId":105405,"popularStar":0},{"itemType":5,"ptpC":"_mb_mls_10057922_wap-index_noab-noab","titleTags":null,"clientUrl":"http://item.meilishuo.com/h5/detail/1lor6li?acm=3.ms.0_4_1lor6li.0.13385-69004.ni0a5r4QXJkto.t_-sd_117-lc_16","iid":"1lor6li","showLarge":{"img":"http://s3.mogucdn.com/mlcdn/55cf19/171229_2i59jfjb0b00k4ej8if20lbg8e14b_1000x1499.jpg_560x999.jpg","w":560,"h":840},"link":"http://item.meilishuo.com/h5/detail/1lor6li?acm=3.ms.0_4_1lor6li.0.13385-69004.ni0a5r4QXJkto.t_-sd_117-lc_16","show":{"img":"http://s11.mogucdn.com/mlcdn/55cf19/171229_2i59jfjb0b00k4ej8if20lbg8e14b_1000x1499.jpg_320x999.jpg","w":320,"h":416},"itemMarks":"1525","acm":"3.ms.0_4_1lor6li.0.13385-69004.ni0a5r4QXJkto.t_-sd_117-lc_16","type":2,"title":"2018秋季新款显瘦金丝绒阔腿裤潮韩版松紧腰休闲裤宽松百搭运动绑带长裤女","orgPrice":"￥128.00","cparam":null,"props":["2018秋季新款显瘦金丝绒阔腿裤潮韩版松紧腰休闲裤宽松百搭运动绑带长裤女"],"lefttop_taglist":[],"sale":710,"price":"55.00","cfav":120,"leftbottom_taglist":[],"shopId":1300725292,"popularStar":0},{"itemType":5,"ptpC":"_mb_mls_10057922_wap-index_noab-noab","titleTags":null,"clientUrl":"http://item.meilishuo.com/h5/detail/1m6z804?acm=3.ms.0_4_1m6z804.0.13385-69004.ni0a5r4QXJkto.t_-sd_117-lc_16","iid":"1m6z804","showLarge":{"img":"http://s11.mogucdn.com/mlcdn/c45406/180807_86h5cg81b1el8kbehk5gicd66bi8j_640x960.jpg_560x999.jpg","w":560,"h":840},"link":"http://item.meilishuo.com/h5/detail/1m6z804?acm=3.ms.0_4_1m6z804.0.13385-69004.ni0a5r4QXJkto.t_-sd_117-lc_16","show":{"img":"http://s11.mogucdn.com/mlcdn/c45406/180807_86h5cg81b1el8kbehk5gicd66bi8j_640x960.jpg_320x999.jpg","w":320,"h":416},"itemMarks":"1525 82","acm":"3.ms.0_4_1m6z804.0.13385-69004.ni0a5r4QXJkto.t_-sd_117-lc_16","type":2,"title":"2018秋季新款韩版宽松百搭V领荷叶边长袖波点衬衫上衣女高腰显瘦修身九分微喇牛仔裤时尚套装","orgPrice":"￥98.58","cparam":null,"props":["2018秋季新款韩版宽松百搭V领荷叶边长袖波点衬衫上衣女高腰显瘦修身九分微喇牛仔裤时尚套装"],"lefttop_taglist":[],"sale":705,"price":"69.00","cfav":60,"leftbottom_taglist":[],"shopId":10664478,"popularStar":0},{"itemType":5,"ptpC":"_mb_mls_10057922_wap-index_noab-noab","titleTags":null,"clientUrl":"http://item.meilishuo.com/h5/detail/1m7jvl2?acm=3.ms.0_4_1m7jvl2.0.13385-69004.ni0a5r4QXJkto.t_-sd_117-lc_16","iid":"1m7jvl2","showLarge":{"img":"http://s3.mogucdn.com/mlcdn/c45406/180822_4hfj3d40b42818ecba1b3j30f5h7a_640x960.jpg_560x999.jpg","w":560,"h":840},"link":"http://item.meilishuo.com/h5/detail/1m7jvl2?acm=3.ms.0_4_1m7jvl2.0.13385-69004.ni0a5r4QXJkto.t_-sd_117-lc_16","show":{"img":"http://s11.mogucdn.com/mlcdn/c45406/180822_4hfj3d40b42818ecba1b3j30f5h7a_640x960.jpg_320x999.jpg","w":320,"h":416},"itemMarks":"1525 2 138 172","acm":"3.ms.0_4_1m7jvl2.0.13385-69004.ni0a5r4QXJkto.t_-sd_117-lc_16","type":2,"title":"秋季新款2018韩版原宿风前后印花宽松长袖卫衣+百搭高腰显瘦抽绳休闲运动裤两件套时尚套装女","orgPrice":"￥82.86","cparam":null,"props":["秋季新款2018韩版原宿风前后印花宽松长袖卫衣+百搭高腰显瘦抽绳休闲运动裤两件套时尚套装女"],"lefttop_taglist":[],"sale":704,"price":"58.00","cfav":35,"leftbottom_taglist":[],"shopId":111011,"popularStar":0},{"itemType":5,"ptpC":"_mb_mls_10057922_wap-index_noab-noab","titleTags":null,"clientUrl":"http://item.meilishuo.com/h5/detail/1m6i2v2?acm=3.ms.0_4_1m6i2v2.0.13385-69004.ni0a5r4QXJkto.t_-sd_117-lc_16","iid":"1m6i2v2","showLarge":{"img":"http://s11.mogucdn.com/mlcdn/c45406/180727_4eke7lifa236h4133cee959g4k874_640x840.jpg_560x999.jpg","w":560,"h":735},"link":"http://item.meilishuo.com/h5/detail/1m6i2v2?acm=3.ms.0_4_1m6i2v2.0.13385-69004.ni0a5r4QXJkto.t_-sd_117-lc_16","show":{"img":"http://s3.mogucdn.com/mlcdn/c45406/180727_4eke7lifa236h4133cee959g4k874_640x840.jpg_320x999.jpg","w":320,"h":416},"itemMarks":"1525 1232","acm":"3.ms.0_4_1m6i2v2.0.13385-69004.ni0a5r4QXJkto.t_-sd_117-lc_16","type":2,"title":"俏果儿 棉麻连衣裙女秋2018新款韩版修身显瘦长裙中长款气质长袖裙子大码女装秋冬装","orgPrice":"￥256.00","cparam":null,"props":["俏果儿 棉麻连衣裙女秋2018新款韩版修身显瘦长裙中长款气质长袖裙子大码女装秋冬装"],"lefttop_taglist":[],"sale":703,"price":"256.00","cfav":14,"leftbottom_taglist":[],"shopId":1302420284,"popularStar":0},{"itemType":5,"ptpC":"_mb_mls_10057922_wap-index_noab-noab","titleTags":null,"clientUrl":"http://item.meilishuo.com/h5/detail/1m7nk44?acm=3.ms.0_4_1m7nk44.0.13385-69004.ni0a5r4QXJkto.t_-sd_117-lc_16","iid":"1m7nk44","showLarge":{"img":"http://s11.mogucdn.com/mlcdn/c45406/180825_664ldb588k7a976l87a5239l05k41_640x960.jpg_560x999.jpg","w":560,"h":840},"link":"http://item.meilishuo.com/h5/detail/1m7nk44?acm=3.ms.0_4_1m7nk44.0.13385-69004.ni0a5r4QXJkto.t_-sd_117-lc_16","show":{"img":"http://s11.mogucdn.com/mlcdn/c45406/180825_664ldb588k7a976l87a5239l05k41_640x960.jpg_320x999.jpg","w":320,"h":416},"itemMarks":"-1","acm":"3.ms.0_4_1m7nk44.0.13385-69004.ni0a5r4QXJkto.t_-sd_117-lc_16","type":2,"title":"2018秋季女装韩版新款灯笼袖针织开衫V领毛衣外套+显瘦纯色百褶时尚百搭长裙两件套装秋装女","orgPrice":"￥198.00","cparam":null,"props":["2018秋季女装韩版新款灯笼袖针织开衫V领毛衣外套+显瘦纯色百褶时尚百搭长裙两件套装秋装女"],"lefttop_taglist":[],"sale":699,"price":"198.00","cfav":59,"leftbottom_taglist":[],"shopId":1302421384,"popularStar":0},{"itemType":5,"ptpC":"_mb_mls_10057922_wap-index_noab-noab","titleTags":null,"clientUrl":"http://item.meilishuo.com/h5/detail/1m6wz72?acm=3.ms.0_4_1m6wz72.0.13385-69004.ni0a5r4QXJkto.t_-sd_117-lc_16","iid":"1m6wz72","showLarge":{"img":"http://s3.mogucdn.com/mlcdn/c45406/180805_5ji51def44321144ak8eg3710gib5_640x960.jpg_560x999.jpg","w":560,"h":840},"link":"http://item.meilishuo.com/h5/detail/1m6wz72?acm=3.ms.0_4_1m6wz72.0.13385-69004.ni0a5r4QXJkto.t_-sd_117-lc_16","show":{"img":"http://s3.mogucdn.com/mlcdn/c45406/180805_5ji51def44321144ak8eg3710gib5_640x960.jpg_320x999.jpg","w":320,"h":416},"itemMarks":"-1","acm":"3.ms.0_4_1m6wz72.0.13385-69004.ni0a5r4QXJkto.t_-sd_117-lc_16","type":2,"title":"2018秋季新款韩版宽松翻领波点系带雪纺衫衬衣+复古显瘦气质弹力修身毛边喇叭裤九分裤两件套","orgPrice":"￥87.15","cparam":null,"props":["2018秋季新款韩版宽松翻领波点系带雪纺衫衬衣+复古显瘦气质弹力修身毛边喇叭裤九分裤两件套"],"lefttop_taglist":[],"sale":698,"price":"61.00","cfav":63,"leftbottom_taglist":[],"shopId":102696,"popularStar":0},{"itemType":5,"ptpC":"_mb_mls_10057922_wap-index_noab-noab","titleTags":null,"clientUrl":"http://item.meilishuo.com/h5/detail/1m7tk32?acm=3.ms.0_4_1m7tk32.0.13385-69004.ni0a5r4QXJkto.t_-sd_117-lc_16","iid":"1m7tk32","showLarge":{"img":"http://s3.mogucdn.com/mlcdn/c45406/180829_73lfgf45ebakglaaa2dak76c30c51_640x960.jpg_560x999.jpg","w":560,"h":840},"link":"http://item.meilishuo.com/h5/detail/1m7tk32?acm=3.ms.0_4_1m7tk32.0.13385-69004.ni0a5r4QXJkto.t_-sd_117-lc_16","show":{"img":"http://s3.mogucdn.com/mlcdn/c45406/180829_73lfgf45ebakglaaa2dak76c30c51_640x960.jpg_320x999.jpg","w":320,"h":416},"itemMarks":"-1","acm":"3.ms.0_4_1m7tk32.0.13385-69004.ni0a5r4QXJkto.t_-sd_117-lc_16","type":2,"title":"时尚套装2018秋装新款女装韩版条纹长袖套头针织衫学院风牛仔背带裤长裤九分牛仔裤子两件套","orgPrice":"￥90.00","cparam":null,"props":["时尚套装2018秋装新款女装韩版条纹长袖套头针织衫学院风牛仔背带裤长裤九分牛仔裤子两件套"],"lefttop_taglist":[],"sale":687,"price":"63.00","cfav":55,"leftbottom_taglist":[],"shopId":10942191,"popularStar":0}],"title":"美丽说wap首页","isEnd":false,"ptpPartC":"_mb_mls_10057922_wap-index_noab-noab","cpc_offset":0}}