{"_id":"5bacc9b251aef28044df8ab4","status":{"code":1001,"msg":""},"result":{"skuInfo":{"title":"时尚套装女2018秋冬新款百搭毛衣女+时尚宽松显瘦牛仔背带裤","skus":[{"stockId":"116kdfwi","xdSkuId":"116kdfwi","price":18000,"nowprice":12600,"img":"//s11.mogucdn.com/mlcdn/55cf19/180822_2ih3kh889f6356h945afi8efjha3l_640x960.jpg","currency":"￥","stock":0,"style":"黑色套装","size":"均码","styleId":1,"sizeId":100},{"stockId":"116kdfwk","xdSkuId":"116kdfwk","price":18000,"nowprice":12600,"img":"//s11.mogucdn.com/mlcdn/55cf19/180822_2ih3kh889f6356h945afi8efjha3l_640x960.jpg","currency":"￥","stock":5990,"style":"黑色套装","size":"S","styleId":1,"sizeId":101},{"stockId":"116kdfwm","xdSkuId":"116kdfwm","price":18000,"nowprice":12600,"img":"//s11.mogucdn.com/mlcdn/55cf19/180822_2ih3kh889f6356h945afi8efjha3l_640x960.jpg","currency":"￥","stock":586,"style":"黑色套装","size":"M","styleId":1,"sizeId":102},{"stockId":"116kdgiw","xdSkuId":"116kdgiw","price":18000,"nowprice":12600,"img":"//s11.mogucdn.com/mlcdn/55cf19/180822_2ih3kh889f6356h945afi8efjha3l_640x960.jpg","currency":"￥","stock":595,"style":"黑色套装","size":"L","styleId":1,"sizeId":103},{"stockId":"116kdgiy","xdSkuId":"116kdgiy","price":18000,"nowprice":12600,"img":"//s11.mogucdn.com/mlcdn/55cf19/180822_2ih3kh889f6356h945afi8efjha3l_640x960.jpg","currency":"￥","stock":595,"style":"黑色套装","size":"XL","styleId":1,"sizeId":104},{"stockId":"116kdgj0","xdSkuId":"116kdgj0","price":18000,"nowprice":12600,"img":"//s3.mogucdn.com/mlcdn/55cf19/180822_4c94ieh5606g8jci2ba3gh7hk45l8_640x960.jpg","currency":"￥","stock":0,"style":"灰色套装","size":"均码","styleId":2,"sizeId":100},{"stockId":"116kdgj2","xdSkuId":"116kdgj2","price":18000,"nowprice":12600,"img":"//s3.mogucdn.com/mlcdn/55cf19/180822_4c94ieh5606g8jci2ba3gh7hk45l8_640x960.jpg","currency":"￥","stock":598,"style":"灰色套装","size":"S","styleId":2,"sizeId":101},{"stockId":"116kdgj4","xdSkuId":"116kdgj4","price":18000,"nowprice":12600,"img":"//s3.mogucdn.com/mlcdn/55cf19/180822_4c94ieh5606g8jci2ba3gh7hk45l8_640x960.jpg","currency":"￥","stock":597,"style":"灰色套装","size":"M","styleId":2,"sizeId":102},{"stockId":"116kdgj6","xdSkuId":"116kdgj6","price":18000,"nowprice":12600,"img":"//s3.mogucdn.com/mlcdn/55cf19/180822_4c94ieh5606g8jci2ba3gh7hk45l8_640x960.jpg","currency":"￥","stock":598,"style":"灰色套装","size":"L","styleId":2,"sizeId":103},{"stockId":"116kdgj8","xdSkuId":"116kdgj8","price":18000,"nowprice":12600,"img":"//s3.mogucdn.com/mlcdn/55cf19/180822_4c94ieh5606g8jci2ba3gh7hk45l8_640x960.jpg","currency":"￥","stock":600,"style":"灰色套装","size":"XL","styleId":2,"sizeId":104},{"stockId":"116kdgjc","xdSkuId":"116kdgjc","price":11286,"nowprice":7900,"img":"//s11.mogucdn.com/mlcdn/55cf19/180822_5l7h2j0kib145a4bb11ig2e8kcgea_640x960.jpg","currency":"￥","stock":0,"style":"单件 黑色背带裤","size":"均码","styleId":3,"sizeId":100},{"stockId":"116kdgja","xdSkuId":"116kdgja","price":11286,"nowprice":7900,"img":"//s11.mogucdn.com/mlcdn/55cf19/180822_5l7h2j0kib145a4bb11ig2e8kcgea_640x960.jpg","currency":"￥","stock":591,"style":"单件 黑色背带裤","size":"S","styleId":3,"sizeId":101},{"stockId":"116kdgje","xdSkuId":"116kdgje","price":11286,"nowprice":7900,"img":"//s11.mogucdn.com/mlcdn/55cf19/180822_5l7h2j0kib145a4bb11ig2e8kcgea_640x960.jpg","currency":"￥","stock":591,"style":"单件 黑色背带裤","size":"M","styleId":3,"sizeId":102},{"stockId":"116kdgjg","xdSkuId":"116kdgjg","price":11286,"nowprice":7900,"img":"//s11.mogucdn.com/mlcdn/55cf19/180822_5l7h2j0kib145a4bb11ig2e8kcgea_640x960.jpg","currency":"￥","stock":597,"style":"单件 黑色背带裤","size":"L","styleId":3,"sizeId":103},{"stockId":"116kdgji","xdSkuId":"116kdgji","price":11286,"nowprice":7900,"img":"//s11.mogucdn.com/mlcdn/55cf19/180822_5l7h2j0kib145a4bb11ig2e8kcgea_640x960.jpg","currency":"￥","stock":600,"style":"单件 黑色背带裤","size":"XL","styleId":3,"sizeId":104},{"stockId":"116kdgjk","xdSkuId":"116kdgjk","price":11286,"nowprice":7900,"img":"//s11.mogucdn.com/mlcdn/55cf19/180822_26akec8j7e335629ede1528b68gi6_640x960.jpg","currency":"￥","stock":0,"style":"单件 灰色背带裤","size":"均码","styleId":4,"sizeId":100},{"stockId":"116kdgjm","xdSkuId":"116kdgjm","price":11286,"nowprice":7900,"img":"//s11.mogucdn.com/mlcdn/55cf19/180822_26akec8j7e335629ede1528b68gi6_640x960.jpg","currency":"￥","stock":599,"style":"单件 灰色背带裤","size":"S","styleId":4,"sizeId":101},{"stockId":"116kdgjo","xdSkuId":"116kdgjo","price":11286,"nowprice":7900,"img":"//s11.mogucdn.com/mlcdn/55cf19/180822_26akec8j7e335629ede1528b68gi6_640x960.jpg","currency":"￥","stock":599,"style":"单件 灰色背带裤","size":"M","styleId":4,"sizeId":102},{"stockId":"116kdgjq","xdSkuId":"116kdgjq","price":11286,"nowprice":7900,"img":"//s11.mogucdn.com/mlcdn/55cf19/180822_26akec8j7e335629ede1528b68gi6_640x960.jpg","currency":"￥","stock":600,"style":"单件 灰色背带裤","size":"L","styleId":4,"sizeId":103},{"stockId":"116kdgjs","xdSkuId":"116kdgjs","price":11286,"nowprice":7900,"img":"//s11.mogucdn.com/mlcdn/55cf19/180822_26akec8j7e335629ede1528b68gi6_640x960.jpg","currency":"￥","stock":600,"style":"单件 灰色背带裤","size":"XL","styleId":4,"sizeId":104},{"stockId":"116kdgju","xdSkuId":"116kdgju","price":9858,"nowprice":6900,"img":"//s11.mogucdn.com/mlcdn/55cf19/180822_3g09e5kg1k9igefklbfdgf8ei7j53_640x960.jpg","currency":"￥","stock":429,"style":"单件 蓝色毛衣","size":"均码","styleId":5,"sizeId":100},{"stockId":"116kdgjw","xdSkuId":"116kdgjw","price":9858,"nowprice":6900,"img":"//s11.mogucdn.com/mlcdn/55cf19/180822_3g09e5kg1k9igefklbfdgf8ei7j53_640x960.jpg","currency":"￥","stock":0,"style":"单件 蓝色毛衣","size":"S","styleId":5,"sizeId":101},{"stockId":"116kdgjy","xdSkuId":"116kdgjy","price":9858,"nowprice":6900,"img":"//s11.mogucdn.com/mlcdn/55cf19/180822_3g09e5kg1k9igefklbfdgf8ei7j53_640x960.jpg","currency":"￥","stock":0,"style":"单件 蓝色毛衣","size":"M","styleId":5,"sizeId":102},{"stockId":"116kdgk0","xdSkuId":"116kdgk0","price":9858,"nowprice":6900,"img":"//s11.mogucdn.com/mlcdn/55cf19/180822_3g09e5kg1k9igefklbfdgf8ei7j53_640x960.jpg","currency":"￥","stock":0,"style":"单件 蓝色毛衣","size":"L","styleId":5,"sizeId":103},{"stockId":"116kdgk2","xdSkuId":"116kdgk2","price":9858,"nowprice":6900,"img":"//s11.mogucdn.com/mlcdn/55cf19/180822_3g09e5kg1k9igefklbfdgf8ei7j53_640x960.jpg","currency":"￥","stock":0,"style":"单件 蓝色毛衣","size":"XL","styleId":5,"sizeId":104}],"props":[{"label":"颜色:","list":[{"type":"style","name":"黑色套装","isDefault":false,"styleId":1,"index":1},{"type":"style","name":"灰色套装","isDefault":false,"styleId":2,"index":2},{"type":"style","name":"单件 黑色背带裤","isDefault":false,"styleId":3,"index":3},{"type":"style","name":"单件 灰色背带裤","isDefault":false,"styleId":4,"index":4},{"type":"style","name":"单件 蓝色毛衣","isDefault":false,"styleId":5,"index":5}],"isDefault":false},{"label":"尺码:","list":[{"type":"size","name":"均码","isDefault":false,"sizeId":100,"index":100},{"type":"size","name":"S","isDefault":false,"sizeId":101,"index":101},{"type":"size","name":"M","isDefault":false,"sizeId":102,"index":102},{"type":"size","name":"L","isDefault":false,"sizeId":103,"index":103},{"type":"size","name":"XL","isDefault":false,"sizeId":104,"index":104}],"isDefault":false}],"styleKey":"颜色","sizeKey":"尺码","priceRange":"¥69.00~¥126.00","defaultPrice":"¥69.00~¥126.00","isAbroad":false,"totalStock":15365},"itemInfo":{"desc":"时尚套装女2018秋冬新款百搭毛衣女+时尚宽松显瘦牛仔背带裤","userId":"11hgvt8","shopId":"14h9i","title":"时尚套装女2018秋冬新款百搭毛衣女+时尚宽松显瘦牛仔背带裤","discountDesc":"7折","discountBgColor":"#f13e3a","lowPrice":"98.58","highPrice":"180.00","lowNowPrice":"69.00","highNowPrice":"126.00","iid":"1m7jhws","isSelf":false,"isFaved":false,"imUrl":"mls://imTalk?&source=1&goodsId=1m7jhws&userId=11hgvt8&shopId=14h9i","state":0,"topImages":["//s3.mogucdn.com/mlcdn/55cf19/180822_891ag27iicc1kl0fa93l0iddg45c3_640x960.jpg","//s11.mogucdn.com/mlcdn/55cf19/180822_762f1401h94j9h7hbfl73c558ed4i_640x960.jpg","//s5.mogucdn.com/mlcdn/55cf19/180822_795cdc0eek65abjh749iagf1269l4_640x960.jpg","//s11.mogucdn.com/mlcdn/55cf19/180822_25iabhb5ai9cef8h68e5laflb6c24_640x960.jpg"],"oldPrice":"¥98.58","price":"¥69.00~¥126.00","saleType":0,"tags":"","inActivity":false,"redPacketsSwitch":false,"cFav":0,"admin":false,"cids":"#682# #683# #2525# #703#","cartNum":0,"extra":{"deliveryTime":72,"sendAddress":"广东省广州市"},"addCartTips":false,"isGrayUser":false,"isNewComer":false},"topBar":{"img":"//s11.mogucdn.com/p1/150811/upload_ieytsmbrmm4wkm3ggizdambqmeyde_226x43.png","link":"http://www.xiaodian.com/h5/download"},"detailInfo":{"desc":"时尚套装女2018秋冬新款百搭毛衣女+时尚宽松显瘦牛仔背带裤","detailImage":[{"desc":"","key":"穿着效果","anchor":"model_img","list":["//s11.mogucdn.com/mlcdn/55cf19/180822_3dab5c16484hi2183e1ekki2i9lbf_750x837.jpg","//s3.mogucdn.com/mlcdn/55cf19/180822_2jk2a7e7k907k870idh7gg5k76b7f_750x978.jpg","//s5.mogucdn.com/mlcdn/55cf19/180822_000eijd4j4ijb6a82ah18h4e1kk45_750x796.jpg","//s11.mogucdn.com/mlcdn/55cf19/180822_77b4kbe51a25fh2la7g41418gbb9c_750x794.jpg","//s5.mogucdn.com/mlcdn/55cf19/180822_401l604aj3ac50i324glf90d10ij0_750x754.jpg","//s5.mogucdn.com/mlcdn/55cf19/180822_53hkgl42hf3i7he3d26b57g127ad2_750x618.jpg","//s11.mogucdn.com/mlcdn/55cf19/180822_69j3cick2g16jh4098fhag7he3jjh_750x698.jpg","//s5.mogucdn.com/mlcdn/55cf19/180822_5k8lgef6d8ch0j8ahedc4gegd44el_750x1008.jpg","//s5.mogucdn.com/mlcdn/55cf19/180822_3i399aekfk1fe672b786f2ig0jj79_750x954.jpg","//s11.mogucdn.com/mlcdn/55cf19/180822_79df14id85h5118j3jj7ddlbl9h78_750x759.jpg","//s11.mogucdn.com/mlcdn/55cf19/180822_41598g8i5jel2ahlbhd3i97g0304g_750x1061.jpg","//s11.mogucdn.com/mlcdn/55cf19/180822_82ddkg52858cl41dbdg4lf59k8di7_750x1091.jpg","//s11.mogucdn.com/mlcdn/55cf19/180822_2f35bcc979ei5dd4kijc6420hb4kg_750x791.jpg","//s3.mogucdn.com/mlcdn/55cf19/180822_2l2ja86i85ed5j9k6l7lc5e3979f5_750x748.jpg","//s5.mogucdn.com/mlcdn/55cf19/180822_0ke22j8ddfghh1cg9d50701l5dgkd_750x1152.jpg","//s11.mogucdn.com/mlcdn/55cf19/180822_6jkfj5gchik382kl8f9c0e9eeb0a2_750x769.jpg","//s11.mogucdn.com/mlcdn/55cf19/180822_0jihja7akbfh795jhbbeb29l84l1j_750x932.jpg","//s11.mogucdn.com/mlcdn/55cf19/180822_37ei7e2ii10c44a473feid9d7lbc2_750x1089.jpg","//s5.mogucdn.com/mlcdn/55cf19/180822_09218hgdbc0h717acc8fkdlhib007_750x1069.jpg","//s11.mogucdn.com/mlcdn/55cf19/180822_4j16ahhj0265ggj4738gl779jgj3g_750x788.jpg","//s11.mogucdn.com/mlcdn/55cf19/180822_7jbe8eil169h554h12el57lhl3572_750x938.jpg","//s11.mogucdn.com/mlcdn/55cf19/180822_5khfi64db0e8jc2b2ab818f6deakf_750x751.jpg","//s5.mogucdn.com/mlcdn/55cf19/180822_8ejlk96ekgcf6g64dc9gij827j987_750x1151.jpg","//s11.mogucdn.com/mlcdn/55cf19/180822_3a31k54a8h7dj07kk1aj7jejgg800_750x623.jpg","//s3.mogucdn.com/mlcdn/55cf19/180822_17h8i1jg8k50e5eaa8gal9bkbj486_750x545.jpg","//s3.mogucdn.com/mlcdn/55cf19/180822_0d46edc0f643h4a9d41l1ca6702k8_750x543.jpg","//s11.mogucdn.com/mlcdn/55cf19/180822_7jalf9bhlhfa0k9fa5hd42ghj43g0_750x537.jpg","//s11.mogucdn.com/mlcdn/55cf19/180822_42e5bg16b4h6jk429f8jg5a0ef55j_750x544.jpg","//s11.mogucdn.com/mlcdn/55cf19/180822_66ia4889712hab614fjif23i1l01j_750x558.jpg","//s11.mogucdn.com/p2/170317/77101615_86e9f0elcl86499l16jf26aallg14_1125x380.jpg"]}]},"columns":["销量 3903","收藏121人","默认快递"],"promotions":{"link":"mls://shoppro?shopId=14h9i","alertData":{},"list":["满2件减3元","满3件减5元","满4件减8元"]},"itemParams":{"info":{"set":[{"value":"色块","key":"图案"},{"value":"普通","key":"厚薄"},{"value":"广东省中山市富忆航服饰有限公司","key":"厂名"},{"value":"灰色套装,黑色套装,单件 蓝色毛衣,单件 灰色背带裤,单件 黑色背带裤","key":"颜色"},{"value":"常规袖","key":"袖型"},{"value":"均码,S,XL,L,M","key":"尺码"},{"value":"常规款（51-65cm）","key":"衣长"},{"value":"秋冬","key":"季节"},{"value":"广东省中山市沙溪镇南康街七号","key":"厂址"},{"value":"牛仔布","key":"材质"},{"value":"圆领","key":"领型"},{"value":"长袖","key":"袖长"},{"value":"衣裤套装","key":"款式"},{"value":"小清新","key":"风格"},{"value":"韩系","key":"潮流"}],"key":"产品参数","anchor":"product_info"},"rule":{"desc":"※ 以上尺寸为实物人工测量，因测量当时不同会有1-2cm误差，相关数据仅作参考，以收到实物为准。","tables":[[["尺码","均码","S","M","L"],["大腿围","-","-","-","-"],["胸围","100","92","96","100"],["腰围","--","-","-","-"],["袖长","45","-","-","-"],["肩宽","45","-","--","-"],["衣长","60","-","-","-"],["臀围","","适合（80-95斤）","适合（95-115斤）","适合（115-130斤）"],["裤长","","110","111","112"]],[["尺码","XL"],["大腿围","-"],["胸围","104"],["腰围","-"],["袖长","-"],["肩宽","-"],["衣长","-"],["臀围","适合（130-155斤）"],["裤长","113"]]],"key":"尺码说明","anchor":"size_info","disclaimer":"※ 以上尺寸为实物人工测量，因测量当时不同会有1-2cm误差，相关数据仅作参考，以收到实物为准。"}},"shopInfo":{"score":[{"name":"描述相符","score":4.72,"isBetter":false},{"name":"价格合理","score":5,"isBetter":true},{"name":"质量满意","score":4.71,"isBetter":false}],"services":[{"name":"延误必赔"},{"icon":"//s11.mogucdn.com/p1/160607/upload_ie4tkmbtgqztomjqhezdambqgqyde_44x44.png","name":"退货补运费"},{"icon":"//s11.mogucdn.com/p1/160607/upload_ie4tkmbtgqztomjqhezdambqgqyde_44x44.png","name":"全国包邮"},{"icon":"//s11.mogucdn.com/p1/160607/upload_ie4tkmbtgqztomjqhezdambqgqyde_44x44.png","name":"7天无理由退货"},{"icon":"//s11.mogucdn.com/p1/160607/upload_ie4tkmbtgqztomjqhezdambqgqyde_44x44.png","name":"72小时发货"}],"categories":[{"name":"针织\\毛衣~","link":"http://s.meilishuo.com/14h9i/list/index?categoryId=8150"},{"name":"裙纸~","link":"http://s.meilishuo.com/14h9i/list/index?categoryId=8151"},{"name":"套装~","link":"http://s.meilishuo.com/14h9i/list/index?categoryId=8162"},{"name":"秋冬12月NEW!!!","link":"http://s.meilishuo.com/14h9i/list/index?categoryId=20148838"},{"name":"外套\\短外套~","link":"http://s.meilishuo.com/14h9i/list/index?categoryId=20242975"},{"name":"寸衫~","link":"http://s.meilishuo.com/14h9i/list/index?categoryId=20243107"},{"name":"牛仔裤\\背带裤","link":"http://s.meilishuo.com/14h9i/list/index?categoryId=20247887"},{"name":"卫衣~","link":"http://s.meilishuo.com/14h9i/list/index?categoryId=20256028"},{"name":"毛呢外套大衣","link":"http://s.meilishuo.com/14h9i/list/index?categoryId=20270513"},{"name":"2018新款","link":"http://s.meilishuo.com/14h9i/list/index?categoryId=20285715"},{"name":"T恤~","link":"http://s.meilishuo.com/14h9i/list/index?categoryId=20309184"}],"cFans":15049,"cSells":234720,"allGoodsUrl":"http://m.meilishuo.com/shop/index/14h9i","shopUrl":"http://m.meilishuo.com/shop/index/14h9i","isMarked":false,"cGoods":387,"userId":"11hgvt8","shopLogo":"//s3.mogucdn.com/b7/pic/141029/qqfvu_ieygmmzygvtgkmjtmqytambqgiyde_320x320.jpg","name":"电话虫","shopId":"14h9i","type":1,"level":4,"nonsupportReasonRefound":false},"rate":{"list":[{"user":{"uid":"","uname":"半夏啪角","avatar":"//s11.mogucdn.com/p2/161214/103488673_527fecjlbb7f05fihi1aggde73jb8_140x140.png","profileUrl":"","tagIndex":""},"rateId":"1167alr8","content":"穿着很漂亮，款式很百搭，质量超级好，做工很好 我很喜欢颜色也很正，穿上很显漂亮.","created":1536805319,"isAnonymous":1,"style":"颜色:单件 蓝色毛衣 尺码:均码 ","isEmpty":0,"explain":"[商家回复]:  感谢亲对我们产品的厚爱与认可，亲的每一个好评都是对我们坚持的鼓励，亲的每一个建议都为我们的前进指明了方向.如果亲收到货对我们的商品有不满意的地方或需要改进的地方，可以及时与我们售后反馈情况。这样我们能够及时改进，才能够提高更好的服务质量同时也能让亲收到更多更好的优质商品宝贝。请您放心，我们将通过不懈的努力将宝贝做得更好，将服务做得更好；一切只为您满意！【Telephone worm美衣】全体团队祝亲和您的家人生活愉快，事事顺心，工作顺利！欢迎您再次光临小店。么么哒","level":"","canExplain":false}],"cRate":15},"isLogin":false,"esi":"<esi:try><esi:attempt><esi:include src='http://m.meilishuo.com/detail/mls/v1/h5_dyn?$(QUERY_STRING)'/></esi:attempt><esi:except></esi:except></esi:try>"},"iid":"1m7jhws"}