{"_id":"5baccd3b51aef2467c7e4afb","status":{"code":1001,"msg":""},"result":{"skuInfo":{"title":"2018秋冬装韩版新款纯色网红同款chic气质高腰圆领长袖修身显瘦3色多选百褶针织连衣裙女","skus":[{"stockId":"117501me","xdSkuId":"117501me","price":17000,"nowprice":11900,"img":"//s5.mogucdn.com/mlcdn/c45406/180926_19ik3j5fck7ckkk7d8h9aj427596h_640x960.jpg","currency":"￥","stock":1000,"style":"灰色","size":"S","styleId":1,"sizeId":100},{"stockId":"117501ma","xdSkuId":"117501ma","price":17000,"nowprice":11900,"img":"//s5.mogucdn.com/mlcdn/c45406/180926_19ik3j5fck7ckkk7d8h9aj427596h_640x960.jpg","currency":"￥","stock":1000,"style":"灰色","size":"M","styleId":1,"sizeId":101},{"stockId":"117501mc","xdSkuId":"117501mc","price":17000,"nowprice":11900,"img":"//s5.mogucdn.com/mlcdn/c45406/180926_19ik3j5fck7ckkk7d8h9aj427596h_640x960.jpg","currency":"￥","stock":1000,"style":"灰色","size":"L","styleId":1,"sizeId":102},{"stockId":"117501m6","xdSkuId":"117501m6","price":17000,"nowprice":11900,"img":"//s11.mogucdn.com/mlcdn/c45406/180926_0ghf5l0j5g3kl7g2ha488kde9dg2b_640x960.jpg","currency":"￥","stock":999,"style":"黑色","size":"S","styleId":2,"sizeId":100},{"stockId":"117501m4","xdSkuId":"117501m4","price":17000,"nowprice":11900,"img":"//s11.mogucdn.com/mlcdn/c45406/180926_0ghf5l0j5g3kl7g2ha488kde9dg2b_640x960.jpg","currency":"￥","stock":1000,"style":"黑色","size":"M","styleId":2,"sizeId":101},{"stockId":"117501m8","xdSkuId":"117501m8","price":17000,"nowprice":11900,"img":"//s11.mogucdn.com/mlcdn/c45406/180926_0ghf5l0j5g3kl7g2ha488kde9dg2b_640x960.jpg","currency":"￥","stock":999,"style":"黑色","size":"L","styleId":2,"sizeId":102},{"stockId":"117501mg","xdSkuId":"117501mg","price":17000,"nowprice":11900,"img":"//s5.mogucdn.com/mlcdn/c45406/180926_4ij3k490bbl1h48g8h22hcge0jja6_640x960.jpg","currency":"￥","stock":1000,"style":"粉色","size":"S","styleId":3,"sizeId":100},{"stockId":"117501mi","xdSkuId":"117501mi","price":17000,"nowprice":11900,"img":"//s5.mogucdn.com/mlcdn/c45406/180926_4ij3k490bbl1h48g8h22hcge0jja6_640x960.jpg","currency":"￥","stock":1000,"style":"粉色","size":"M","styleId":3,"sizeId":101},{"stockId":"117501mk","xdSkuId":"117501mk","price":17000,"nowprice":11900,"img":"//s5.mogucdn.com/mlcdn/c45406/180926_4ij3k490bbl1h48g8h22hcge0jja6_640x960.jpg","currency":"￥","stock":1000,"style":"粉色","size":"L","styleId":3,"sizeId":102},{"stockId":"117501mm","xdSkuId":"117501mm","price":17000,"nowprice":11900,"img":"//s11.mogucdn.com/mlcdn/c45406/180926_1kgi1ag6i89b9bhekh886hgc9l115_640x960.jpg","currency":"￥","stock":999,"style":"南瓜色","size":"S","styleId":4,"sizeId":100},{"stockId":"117501mo","xdSkuId":"117501mo","price":17000,"nowprice":11900,"img":"//s11.mogucdn.com/mlcdn/c45406/180926_1kgi1ag6i89b9bhekh886hgc9l115_640x960.jpg","currency":"￥","stock":1000,"style":"南瓜色","size":"M","styleId":4,"sizeId":101},{"stockId":"117501mq","xdSkuId":"117501mq","price":17000,"nowprice":11900,"img":"//s11.mogucdn.com/mlcdn/c45406/180926_1kgi1ag6i89b9bhekh886hgc9l115_640x960.jpg","currency":"￥","stock":1000,"style":"南瓜色","size":"L","styleId":4,"sizeId":102}],"props":[{"label":"颜色:","list":[{"type":"style","name":"灰色","isDefault":false,"styleId":1,"index":1},{"type":"style","name":"黑色","isDefault":false,"styleId":2,"index":2},{"type":"style","name":"粉色","isDefault":false,"styleId":3,"index":3},{"type":"style","name":"南瓜色","isDefault":false,"styleId":4,"index":4}],"isDefault":false},{"label":"尺码:","list":[{"type":"size","name":"S","isDefault":false,"sizeId":100,"index":100},{"type":"size","name":"M","isDefault":false,"sizeId":101,"index":101},{"type":"size","name":"L","isDefault":false,"sizeId":102,"index":102}],"isDefault":false}],"styleKey":"颜色","sizeKey":"尺码","priceRange":"¥119.00","defaultPrice":"¥119.00","isAbroad":false,"totalStock":11997},"itemInfo":{"desc":"2018秋冬装韩版新款纯色网红同款chic气质高腰圆领长袖修身显瘦3色多选百褶针织连衣裙女","userId":"19lu0gy","shopId":"1172usqy","title":"2018秋冬装韩版新款纯色网红同款chic气质高腰圆领长袖修身显瘦3色多选百褶针织连衣裙女","discountDesc":"7折","discountBgColor":"#f13e3a","lowPrice":"170.00","highPrice":"170.00","lowNowPrice":"119.00","highNowPrice":"119.00","iid":"1m9204a","isSelf":false,"isFaved":false,"imUrl":"mls://imTalk?&source=1&goodsId=1m9204a&userId=19lu0gy&shopId=1172usqy","state":0,"topImages":["//s3.mogucdn.com/mlcdn/c45406/180926_8641c6ci3b908di8857kle2bi4aig_640x960.jpg","//s11.mogucdn.com/mlcdn/c45406/180926_853e2fce8i0ad61ehcbkab18b5cgl_640x960.jpg","//s3.mogucdn.com/mlcdn/c45406/180926_80cfdj4ff67l200cjib066bb121j4_640x960.jpg","//s11.mogucdn.com/mlcdn/c45406/180926_3h5bi7ckh77hfb940hgfkl9gckjj6_640x960.jpg","//s3.mogucdn.com/mlcdn/c45406/180926_7k59j02i39b1e9klek49jdk2d9gge_640x960.jpg","//s11.mogucdn.com/mlcdn/c45406/180926_4951lcha978fhh9i5cd5ail2dgbh9_640x960.jpg","//s5.mogucdn.com/mlcdn/c45406/180926_61kfcd7c8e90fehj81be885f3k300_640x960.jpg","//s11.mogucdn.com/mlcdn/c45406/180926_58bhjkf10ekd31b17dk0k5bfbdhe3_640x960.jpg"],"oldPrice":"¥170.00","price":"¥119.00","saleType":0,"tags":"","inActivity":false,"redPacketsSwitch":false,"cFav":0,"admin":false,"cids":"#682# #683# #704# #705#","cartNum":0,"extra":{"deliveryTime":72,"sendAddress":""},"addCartTips":false,"isGrayUser":false,"isNewComer":false},"topBar":{"img":"//s11.mogucdn.com/p1/150811/upload_ieytsmbrmm4wkm3ggizdambqmeyde_226x43.png","link":"http://www.xiaodian.com/h5/download"},"detailInfo":{"desc":"2018秋冬装韩版新款纯色网红同款chic气质高腰圆领长袖修身显瘦3色多选百褶针织连衣裙女","detailImage":[{"desc":"","key":"穿着效果","anchor":"model_img","list":["//s5.mogucdn.com/mlcdn/c45406/180926_6fhbfkcle91e9kfb7g81igg92iekl_750x960.jpg","//s3.mogucdn.com/mlcdn/c45406/180926_526ef5695h1jh4860khff8dea35i5_750x959.jpg","//s11.mogucdn.com/mlcdn/c45406/180926_15g95jij36k738h6dg4k5ic74i83f_750x863.jpg","//s11.mogucdn.com/mlcdn/c45406/180926_53599d13kd70df67b1756k0i1cf41_750x1008.jpg","//s11.mogucdn.com/mlcdn/c45406/180926_2k47kaaeba6d6kjlkb63g1e4gcjih_750x991.jpg","//s5.mogucdn.com/mlcdn/c45406/180926_5lclab40kfeddg2j97b3ab8ac0ac5_750x973.jpg","//s11.mogucdn.com/mlcdn/c45406/180926_284ddlj5h0g2c4898aka00e1ejk9b_750x1028.jpg","//s11.mogucdn.com/mlcdn/c45406/180926_8ge0c83adje7ii51ib1d7a3hidg6h_750x783.jpg","//s11.mogucdn.com/mlcdn/c45406/180926_155eg0c45354bac2dai92e64eh091_750x894.jpg","//s3.mogucdn.com/mlcdn/c45406/180926_3fj10k9jb373lh55lde19fg8jd51h_750x1194.jpg","//s5.mogucdn.com/mlcdn/c45406/180926_0ea79i9i3k458f7fl59ek202hcf23_750x1035.jpg","//s3.mogucdn.com/mlcdn/c45406/180926_2597kk57a7l2i55gi133kebhli1ke_750x832.jpg","//s11.mogucdn.com/mlcdn/c45406/180926_3be1gg3lj2bd2igblci31l7e8bi8f_750x922.jpg","//s11.mogucdn.com/mlcdn/c45406/180926_2fjk8g9edl1ga78ee4el1b32bljka_750x921.jpg","//s5.mogucdn.com/mlcdn/c45406/180926_5g4clj2772d50k74ci32j48i0ehhh_750x1179.jpg","//s11.mogucdn.com/mlcdn/c45406/180926_1i845hgjklk60jffeij467b31h0f5_750x878.jpg","//s5.mogucdn.com/mlcdn/c45406/180926_71g2k29dagaikl40j58j4760h97ld_750x1030.jpg","//s5.mogucdn.com/mlcdn/c45406/180926_09bj70kl8c9j0h6ci791bc8bh0agd_750x1039.jpg","//s11.mogucdn.com/mlcdn/c45406/180926_7e97i9f6758dlkk4j8l00ci0gadfk_750x959.jpg","//s11.mogucdn.com/mlcdn/c45406/180926_8h36g5ah4ejlkd9f75i545klg56lb_750x863.jpg","//s5.mogucdn.com/mlcdn/c45406/180926_04jff22fb0i2jj116168428e1jc13_750x1120.jpg","//s11.mogucdn.com/mlcdn/c45406/180926_76g3h4740ic0dk9gd8e20hbj1cib1_750x991.jpg","//s11.mogucdn.com/mlcdn/c45406/180926_5391419e5jb4i7jahacd4i7lk1f2f_750x1070.jpg","//s11.mogucdn.com/mlcdn/c45406/180926_3ab0j7i9k2l6a3235b57e9jch89da_750x1277.jpg","//s11.mogucdn.com/mlcdn/c45406/180926_5bgc3h7akf91kkbgf279dfb3c2d4h_750x1010.jpg","//s11.mogucdn.com/mlcdn/c45406/180926_694haii834kg05llb52k22fbfj3g3_750x936.jpg","//s11.mogucdn.com/mlcdn/c45406/180926_8eefc7klbl795lfaehd069e7j0f6h_750x945.jpg","//s5.mogucdn.com/mlcdn/c45406/180926_76l4975e0i7hil1ida800adegj24h_750x946.jpg","//s11.mogucdn.com/mlcdn/c45406/180926_314li9b0ca704ak057c0iiadkl17h_750x683.jpg","//s3.mogucdn.com/mlcdn/c45406/180926_8a52k189ehffc071b1b2ii1ej35bi_750x1119.jpg","//s11.mogucdn.com/mlcdn/c45406/180926_1jd55079h75i24l1cbbkj2l7dii69_750x1033.jpg","//s5.mogucdn.com/mlcdn/c45406/180926_70jaeg48e7i419354hhej8ak20ie0_750x1179.jpg","//s5.mogucdn.com/mlcdn/c45406/180926_09alh91gbib41kj1d896lge82k49g_750x878.jpg","//s3.mogucdn.com/mlcdn/c45406/180926_849cicid9ghge4957eci5c8512jb7_750x1139.jpg","//s3.mogucdn.com/mlcdn/c45406/180926_8fih5ki9872bdld742708e195cf37_750x1037.jpg","//s11.mogucdn.com/mlcdn/c45406/180926_4k1g0ld3ab659el0l5ja4ddbk73gc_750x1157.jpg","//s3.mogucdn.com/mlcdn/c45406/180926_5k7ehh1i3592alj39983ib5aab4ac_750x1142.jpg","//s11.mogucdn.com/mlcdn/c45406/180926_7gbb15d06kk14e7fa9b6071fe98h8_750x1020.jpg","//s11.mogucdn.com/mlcdn/c45406/180926_610d9d35c1j94aj6lf6e0a3beb5ge_750x1039.jpg","//s11.mogucdn.com/mlcdn/c45406/180926_68lh73gi84ba8j36863h0ak1f0h5g_750x959.jpg","//s11.mogucdn.com/mlcdn/c45406/180926_0ak1aae4jc877jbe0h23f5le6317l_750x702.jpg","//s5.mogucdn.com/mlcdn/c45406/180926_00eb099k554k5279ibcgh5a2j0ij5_750x1120.jpg","//s5.mogucdn.com/mlcdn/c45406/180926_5ff05ldc0hkj89j7ehjkcg61lad93_750x991.jpg","//s11.mogucdn.com/mlcdn/c45406/180926_7245eic6067j139bcjai0b6adkdac_750x1070.jpg","//s3.mogucdn.com/mlcdn/c45406/180926_609ie8fhh7e6a5ieic41d42gkg88d_750x1277.jpg","//s11.mogucdn.com/mlcdn/c45406/180926_0f8kje6194jeflhgleh4kefgl6d03_750x1010.jpg","//s11.mogucdn.com/mlcdn/c45406/180926_5110kjjj2522i2hi8806debe7ee5k_750x936.jpg","//s11.mogucdn.com/mlcdn/c45406/180926_403k8k4ah1ldke58fad0012e9e4k8_750x1194.jpg","//s11.mogucdn.com/mlcdn/c45406/180926_7e2bih4al3fg337g6bh7c2h9l3afl_750x1119.jpg","//s11.mogucdn.com/mlcdn/c45406/180926_184k46313bh3dcbide8k241a9dd3h_750x930.jpg","//s5.mogucdn.com/mlcdn/c45406/180926_5ekl41k941671dbjij0g2l718ih8c_750x1020.jpg","//s3.mogucdn.com/mlcdn/c45406/180926_1d60i6968b20j6dg89l4769c61b48_750x1039.jpg","//s5.mogucdn.com/mlcdn/c45406/180926_7j39c0laha1c50h4535403akeceg8_750x959.jpg","//s5.mogucdn.com/mlcdn/c45406/180926_3251k4a5cg347ihf55dc8c6jcdae3_750x863.jpg","//s11.mogucdn.com/p2/170317/77101615_86e9f0elcl86499l16jf26aallg14_1125x380.jpg"]}]},"columns":["销量 3","收藏0人","默认快递"],"itemParams":{"info":{"set":[{"value":"纯色","key":"图案"},{"value":"广州市炬美电子科技有限公司","key":"厂名"},{"value":"A字裙","key":"裙型"},{"value":"黑色,粉色,南瓜色,灰色","key":"颜色"},{"value":"常规袖","key":"袖型"},{"value":"套头","key":"衣门襟"},{"value":"常规","key":"摆型"},{"value":"高腰","key":"腰型"},{"value":"S,L,M","key":"尺码"},{"value":"A型","key":"版型"},{"value":"秋冬","key":"季节"},{"value":"广东省广州市海珠区泉塘路28号","key":"厂址"},{"value":"其他","key":"材质"},{"value":"单件","key":"组合形式"},{"value":"圆领","key":"领型"},{"value":"中长裙（106-125cm）","key":"裙长"},{"value":"长袖","key":"袖长"},{"value":"甜美","key":"风格"},{"value":"韩系","key":"潮流"}],"key":"产品参数","anchor":"product_info"},"rule":{"tables":[[["尺码","S","M","L"],["裙长","102","105","108"],["肩宽","54","55","56"],["胸围","78","82","86"],["袖长","65","66.5","68"]]],"key":"尺码说明","anchor":"size_info","disclaimer":"※ 以上尺寸为实物人工测量，因测量当时不同会有1-2cm误差，相关数据仅作参考，以收到实物为准。"}},"shopInfo":{"score":[{"name":"描述相符","score":4.94,"isBetter":true},{"name":"价格合理","score":5,"isBetter":true},{"name":"质量满意","score":4.95,"isBetter":true}],"services":[{"name":"延误必赔"},{"icon":"//s11.mogucdn.com/p1/160607/upload_ie4tkmbtgqztomjqhezdambqgqyde_44x44.png","name":"退货补运费"},{"icon":"//s11.mogucdn.com/p1/160607/upload_ie4tkmbtgqztomjqhezdambqgqyde_44x44.png","name":"7天无理由退货"},{"icon":"//s11.mogucdn.com/p1/160607/upload_ie4tkmbtgqztomjqhezdambqgqyde_44x44.png","name":"72小时发货"}],"categories":[{"name":"【上装】","link":"http://s.meilishuo.com/1172usqy/list/index?categoryId=20323947"},{"name":"T恤","link":"http://s.meilishuo.com/1172usqy/list/index?categoryId=20323948"},{"name":"衬衫","link":"http://s.meilishuo.com/1172usqy/list/index?categoryId=20323949"},{"name":"牛仔外套","link":"http://s.meilishuo.com/1172usqy/list/index?categoryId=20323950"},{"name":"棒球服外套","link":"http://s.meilishuo.com/1172usqy/list/index?categoryId=20323951"},{"name":"针织衫","link":"http://s.meilishuo.com/1172usqy/list/index?categoryId=20323952"},{"name":"【下装】","link":"http://s.meilishuo.com/1172usqy/list/index?categoryId=20323953"},{"name":"短裤/热裤","link":"http://s.meilishuo.com/1172usqy/list/index?categoryId=20323954"},{"name":"长裤/牛仔裤","link":"http://s.meilishuo.com/1172usqy/list/index?categoryId=20323955"},{"name":"休闲/阔腿裤","link":"http://s.meilishuo.com/1172usqy/list/index?categoryId=20323956"},{"name":"棉服","link":"http://s.meilishuo.com/1172usqy/list/index?categoryId=20323959"},{"name":"【裙子】","link":"http://s.meilishuo.com/1172usqy/list/index?categoryId=20323962"},{"name":"半身裙","link":"http://s.meilishuo.com/1172usqy/list/index?categoryId=20323963"},{"name":"连衣裙","link":"http://s.meilishuo.com/1172usqy/list/index?categoryId=20323964"},{"name":"【时尚套装】","link":"http://s.meilishuo.com/1172usqy/list/index?categoryId=20323965"},{"name":"休闲裤","link":"http://s.meilishuo.com/1172usqy/list/index?categoryId=20339231"},{"name":"毛呢外套","link":"http://s.meilishuo.com/1172usqy/list/index?categoryId=20339232"},{"name":"皮草外套","link":"http://s.meilishuo.com/1172usqy/list/index?categoryId=20339620"},{"name":"风衣外套","link":"http://s.meilishuo.com/1172usqy/list/index?categoryId=20340917"},{"name":"长袖-卫衣","link":"http://s.meilishuo.com/1172usqy/list/index?categoryId=20345092"}],"cFans":1941,"cSells":16072,"allGoodsUrl":"http://m.meilishuo.com/shop/index/1172usqy","shopUrl":"http://m.meilishuo.com/shop/index/1172usqy","isMarked":false,"cGoods":274,"userId":"19lu0gy","shopLogo":"//s5.mogucdn.com/mlcdn/c45406/180428_4idb23784aadfie3aef0a93c5edk3_200x200.jpg","name":"焕新衣柜","shopId":"1172usqy","type":2,"level":5,"nonsupportReasonRefound":false},"rate":{"cRate":0,"imgTotal":0},"isLogin":false,"esi":"<esi:try><esi:attempt><esi:include src='http://m.meilishuo.com/detail/mls/v1/h5_dyn?$(QUERY_STRING)'/></esi:attempt><esi:except></esi:except></esi:try>"},"iid":"1m9204a"}