{"_id":"5bacccaf51aef2467c7e4933","status":{"code":1001,"msg":""},"result":{"skuInfo":{"title":"夏装2018新款小清新海边度假沙滩裙长裙00吊带雪纺碎花连衣裙女","skus":[{"stockId":"1175gyxm","xdSkuId":"1175gyxm","price":5713,"nowprice":5713,"img":"//s3.mogucdn.com/mlcdn/c45406/180927_280f1abicb0ej60c6d8a8gaac9cha_900x900.jpg","currency":"￥","stock":500,"style":"藏青底菠萝","size":"M","styleId":1,"sizeId":100},{"stockId":"1175gyxo","xdSkuId":"1175gyxo","price":5713,"nowprice":5713,"img":"//s3.mogucdn.com/mlcdn/c45406/180927_280f1abicb0ej60c6d8a8gaac9cha_900x900.jpg","currency":"￥","stock":500,"style":"藏青底菠萝","size":"L","styleId":1,"sizeId":101},{"stockId":"1175gyxq","xdSkuId":"1175gyxq","price":5713,"nowprice":5713,"img":"//s11.mogucdn.com/mlcdn/c45406/180927_65c72lbga2fjli7c9j5lh1c448jk0_900x899.jpg","currency":"￥","stock":500,"style":"湖蓝底菠萝","size":"M","styleId":2,"sizeId":100},{"stockId":"1175gyxs","xdSkuId":"1175gyxs","price":5713,"nowprice":5713,"img":"//s11.mogucdn.com/mlcdn/c45406/180927_65c72lbga2fjli7c9j5lh1c448jk0_900x899.jpg","currency":"￥","stock":500,"style":"湖蓝底菠萝","size":"L","styleId":2,"sizeId":101},{"stockId":"1175gyxu","xdSkuId":"1175gyxu","price":5713,"nowprice":5713,"img":"//s11.mogucdn.com/mlcdn/c45406/180927_723g98ghjke2igb0952ic2gg1ed18_900x900.jpg","currency":"￥","stock":500,"style":"粉色底菠萝","size":"M","styleId":3,"sizeId":100},{"stockId":"1175gyxw","xdSkuId":"1175gyxw","price":5713,"nowprice":5713,"img":"//s11.mogucdn.com/mlcdn/c45406/180927_723g98ghjke2igb0952ic2gg1ed18_900x900.jpg","currency":"￥","stock":500,"style":"粉色底菠萝","size":"L","styleId":3,"sizeId":101},{"stockId":"1175gyxy","xdSkuId":"1175gyxy","price":5713,"nowprice":5713,"img":"//s5.mogucdn.com/mlcdn/c45406/180927_770cif6dh0k6k7758e8bbb07c881k_900x900.jpg","currency":"￥","stock":500,"style":"白色底菠萝","size":"M","styleId":4,"sizeId":100},{"stockId":"1175gyy0","xdSkuId":"1175gyy0","price":5713,"nowprice":5713,"img":"//s5.mogucdn.com/mlcdn/c45406/180927_770cif6dh0k6k7758e8bbb07c881k_900x900.jpg","currency":"￥","stock":500,"style":"白色底菠萝","size":"L","styleId":4,"sizeId":101}],"props":[{"label":"颜色:","list":[{"type":"style","name":"藏青底菠萝","isDefault":false,"styleId":1,"index":1},{"type":"style","name":"湖蓝底菠萝","isDefault":false,"styleId":2,"index":2},{"type":"style","name":"粉色底菠萝","isDefault":false,"styleId":3,"index":3},{"type":"style","name":"白色底菠萝","isDefault":false,"styleId":4,"index":4}],"isDefault":false},{"label":"尺码:","list":[{"type":"size","name":"M","isDefault":false,"sizeId":100,"index":100},{"type":"size","name":"L","isDefault":false,"sizeId":101,"index":101}],"isDefault":false}],"styleKey":"颜色","sizeKey":"尺码","priceRange":"¥57.13","defaultPrice":"¥57.13","isAbroad":false,"totalStock":4000},"itemInfo":{"desc":"夏装2018新款小清新海边度假沙滩裙长裙00吊带雪纺碎花连衣裙女","userId":"1arcnhw","shopId":"1172uyp0","title":"夏装2018新款小清新海边度假沙滩裙长裙00吊带雪纺碎花连衣裙女","discountDesc":"","discountBgColor":"#f13e3a","lowPrice":"57.13","highPrice":"57.13","lowNowPrice":"57.13","highNowPrice":"57.13","iid":"1m93a4i","isSelf":false,"isFaved":false,"imUrl":"mls://imTalk?&source=1&goodsId=1m93a4i&userId=1arcnhw&shopId=1172uyp0","state":0,"topImages":["//s11.mogucdn.com/mlcdn/c45406/180927_81109kl33ji4hci0i5djb5bh7fk96_640x960.jpg"],"price":"¥57.13","saleType":0,"tags":"","inActivity":false,"redPacketsSwitch":false,"cFav":0,"admin":false,"cids":"#682# #683# #704# #705#","cartNum":0,"extra":{"mobilePrice":"39.99","mobileDownloadLink":"https://a.app.qq.com/o/simple.jsp?pkgname=com.mogujie","deliveryTime":72,"sendAddress":""},"addCartTips":false,"isGrayUser":false,"isNewComer":false},"topBar":{"img":"//s11.mogucdn.com/p1/150811/upload_ieytsmbrmm4wkm3ggizdambqmeyde_226x43.png","link":"http://www.xiaodian.com/h5/download"},"detailInfo":{"desc":"夏装2018新款小清新海边度假沙滩裙长裙00吊带雪纺碎花连衣裙女","detailImage":[{"desc":"","key":"穿着效果","anchor":"model_img","list":["//s11.mogucdn.com/mlcdn/c45406/180927_6gb3k5calg76gd45ed606154287il_900x900.jpg","//s11.mogucdn.com/mlcdn/c45406/180927_75i8i0lk4f7ekc4e0d42a4e4ef1a3_900x900.jpg","//s11.mogucdn.com/mlcdn/c45406/180927_1c9k683b694ja8hhl3c50c3iaeg82_900x899.jpg","//s11.mogucdn.com/mlcdn/c45406/180927_6i9bb4aedf97070557bce1a1ag04g_900x900.jpg","//s11.mogucdn.com/mlcdn/c45406/180927_0kgb2499aa2gf9j2g4f5la6h936k7_900x900.jpg","//s11.mogucdn.com/mlcdn/c45406/180927_1715c1316d8bb83d713cie1j3929b_900x900.jpg","//s5.mogucdn.com/mlcdn/c45406/180927_7a6ja1889h5ej68f0d3e58i3ak2dc_900x900.jpg","//s11.mogucdn.com/mlcdn/c45406/180927_32753b64f5iae4ibfbge36geak15l_900x900.jpg","//s3.mogucdn.com/mlcdn/c45406/180927_09k1jd17g90ah2d9lbbfj8c34e3ib_900x899.jpg","//s11.mogucdn.com/mlcdn/c45406/180927_270f8lk6f66f5jcd20gc039kgf936_900x900.jpg","//s3.mogucdn.com/mlcdn/c45406/180927_5j40g3hca17ej0j1h3eeb6d239d66_900x900.jpg","//s11.mogucdn.com/mlcdn/c45406/180927_50790lc0lb4ad2cj3451b3diedhjl_900x899.jpg","//s11.mogucdn.com/mlcdn/c45406/180927_0kggg3hfa2clkd7blk23fkb2571b1_900x900.jpg","//s11.mogucdn.com/mlcdn/c45406/180927_660hldfl89e8a9ie5j90l7ghlj5d3_900x900.jpg","//s11.mogucdn.com/mlcdn/c45406/180927_4b9acibg82jfai4haahchejl9hahe_900x900.jpg","//s11.mogucdn.com/mlcdn/c45406/180927_4i1hbfl2dk2aa777fc4f1lj8ga888_900x900.jpg","//s11.mogucdn.com/p2/170317/77101615_86e9f0elcl86499l16jf26aallg14_1125x380.jpg"]}]},"columns":["销量 0","收藏0人","默认快递"],"itemParams":{"info":{"set":[{"value":"水果/食物","key":"图案"},{"value":"东湖湾公司","key":"厂名"},{"value":"吊带裙","key":"裙型"},{"value":"湖蓝底菠萝,粉色底菠萝,藏青底菠萝,白色底菠萝","key":"颜色"},{"value":"中腰","key":"腰型"},{"value":"L,M","key":"尺码"},{"value":"秋季","key":"季节"},{"value":"福建省莆田市城厢区霞林街道澄湖小区","key":"厂址"},{"value":"其他","key":"材质"},{"value":"单件","key":"组合形式"},{"value":"V领","key":"领型"},{"value":"中长裙（106-125cm）","key":"裙长"},{"value":"无袖","key":"袖长"},{"value":"简约","key":"风格"}],"key":"产品参数","anchor":"product_info"},"rule":{"tables":[[["尺码","M","L"],["裙长","88","88"],["胸围","94","96"]]],"key":"尺码说明","anchor":"size_info","disclaimer":"※ 以上尺寸为实物人工测量，因测量当时不同会有1-2cm误差，相关数据仅作参考，以收到实物为准。"}},"shopInfo":{"score":[{"name":"描述相符","score":4.65,"isBetter":false},{"name":"价格合理","score":5,"isBetter":true},{"name":"质量满意","score":4.65,"isBetter":false}],"services":[{"icon":"//s11.mogucdn.com/p1/160607/upload_ie4tkmbtgqztomjqhezdambqgqyde_44x44.png","name":"7天无理由退货"},{"icon":"//s11.mogucdn.com/p1/160607/upload_ie4tkmbtgqztomjqhezdambqgqyde_44x44.png","name":"72小时发货"},{"icon":"//s11.mogucdn.com/p1/160607/upload_ie4tkmbtgqztomjqhezdambqgqyde_44x44.png","name":"退货补运费"}],"cFans":24,"cSells":7551,"allGoodsUrl":"http://m.meilishuo.com/shop/index/1172uyp0","shopUrl":"http://m.meilishuo.com/shop/index/1172uyp0","isMarked":false,"cGoods":400,"userId":"1arcnhw","shopLogo":"//s5.mogucdn.com/pic/141211/1agxqe_ieygmodbmiztmzrqmuytambqmmyde_120x120.jpg","name":"欧蓄旗舰店","shopId":"1172uyp0","type":2,"level":3,"nonsupportReasonRefound":false},"rate":{"cRate":0,"imgTotal":0},"isLogin":false,"esi":"<esi:try><esi:attempt><esi:include src='http://m.meilishuo.com/detail/mls/v1/h5_dyn?$(QUERY_STRING)'/></esi:attempt><esi:except></esi:except></esi:try>"},"iid":"1m93a4i"}